{"kQUhenpzduzAMrDu7t7Mhw==":"dsc05842-2000x1122.jpg","dfpao8XAukPHnShAhFlHjg==":"restaurant-media-12580-b-2000x1334.jpg","Dt/bf+/QTmhlCPLLdIimeQ==":"dsc-2000x1333.jpg","jjUvXAdK7VTTgvc3viey/A==":"mg-2000x1333.jpg","775CaYw0LMWDplXVcuuwnw==":"7-reasons-why-you-should-go-camping-this-summer-2000x1500.jpg","TFkrIIxbnGeaq/xg/TdFmQ==":"tiger-lounge-2000x970.jpg","YlImZQNQ+PKUBVUwm426Dw==":"felix-2000x1332.jpg","lqeWFwxe7rNuQd3ch04GGQ==":"204877951_x-2000x1328.jpg","csGQGbyQm6zJ0S5K4rrk4A==":"49f04b540a_800x600-2000x1500.png","4HJ9xVzxqD+XJfrguBzx7g==":"4-ways-to-make-your-workspace-work-for-you-2000x1551.jpg","Z/4ui2le8l+xLnOWrNI7Ig==":"kitchen-classroom-2000x1313.jpg","Q9vOTkdhHGTpdYYUHiefVQ==":"%E4%B8%8B%E8%BC%89%20(1)-2000x2000.jpg","hew2QZZ87GBKdZ3kHywLEg==":"2b0f0fb7dd3ad0cc2d3f8d1c7e82d294-2000x1338.jpg","2YxgtcIGyV4cKEyFoKGCYg==":"%E5%B0%8F%E7%A2%A7%E6%BD%AD%E7%B6%B2%E7%90%83%E5%A0%B4-2000x1500.jpg","m7KC6CLmLy/dxXgZfxpHnA==":"study-rooms-2000x1125.jpg","7uHtvBfFz3PEUyeAjhEc2Q==":"studyroom_web-2000x979.jpg","jUd6FmQq2DP2aXWGdp8OFg==":"silent_study_room_1-2000x1500.jpg","SVkBg0sdClYDuHAyWKkWlA==":"small-study-room-traditional-design-small-study-room-design-ideas-1297d3fcfa0ea746-2000x1500.jpg","E2Z0txZ/K8o6nXkA5DBPZA==":"how-to-upgrade-your-hotel-room-for-free-2000x1250.jpg","bYZQfGoLBYWzYD7jQXwY7g==":"45_0e29a21e-2000x1319.jpg","6zr76xfZcLMWyDY7qzqXLg==":"avayastadium_final_updated-2000x1331.jpg","hluyVfW+zrtNaybpezw5zQ==":"0-2000x1333.jpg","eQU1xf5uiSp1XoP6lzWbYg==":"img-2000x1477.jpg","xxttSTj3Ag+srFDg22jOhA==":"beach-view-rooms-2000x1333.jpg","15SLUdWYAaLJoKKHVrGI/g==":"the-walking-dead-logo-white-c-408x128.png","J1mpgh+j5IkQISq1N7g63A==":"the-walking-dead-season-7-rick-lincoln-michonne-gurira-cci-key-art-1200x707-1-2000x1178.jpg","WXJc9mVE6LISsXl7ymX+Ng==":"maxresdefault-2000x1125.jpg","yDnyJh/1YhzhzfVqDCgaVQ==":"the-walking-dead-season-7-negan-2000x1000.jpg","kl6AxqQYMA0EDZ6Rus/OoQ==":"twd_701_apr17_big-2000x1125.jpg","fGx/YvQOb37FwKwh6eh2Yw==":"twd_702_apr17_big-2000x1125.jpg","G+LppXaA6TgNRYCYo7Ch8Q==":"twd_703_apr17_big-2000x1125.jpg","3SrgoStPXrfeBO19J743uQ==":"twd_704_apr17_big-2000x1125.jpg","LldNVdSTF6b8X2Zf6QS72w==":"twd_705_apr17_big-2000x1125.jpg","7WR5duwpF4zzrnT2TxGqGQ==":"twd_706_apr17_big-2000x1125.jpg","Tl8HKW9e+khqu5rn0amVnw==":"twd_707_apr17_big-2000x1125.jpg","4piSAuTkgkP5I3153Fxg3g==":"twd_708_apr17_big-2000x1125.jpg","7VCdZQYBnK9E6RmDvNJLow==":"twd_709_d1-2000x1125.jpg","Fmc8NpQM+1cLOXYP5OQBRw==":"twd_710_d1-2000x1125.jpg","6e6OtLs3194VFH2l3hYqkw==":"twd_711_d1-2000x1125.jpg","Q5m0RlDgHDsU8jdeRxkBhw==":"twd_712_d1-2000x1125.jpg","QkubdJuTD8Yo2OWaWehTIA==":"twd_713_d1-2000x1125.jpg","dpDJsCFHHxTF3mPLL3BWrA==":"twd_714_d1-2000x1125.jpg","x17ZeYbLxPaT9mecXsBStg==":"twd_715_d1-2000x1125.jpg","vm+hQuGzKr2qxq6ohn/6Sg==":"twd_716_d1-2000x1125.jpg","/g1hdIK17iOiVTVxGShDYA==":"the-walking-dead-logo-white-c-265x83.png","r6XN4v5ATSsmHmM046Uh6A==":"tvcomlogous-600x122.png","yBULxQVXI70rgf/wn6dZrg==":"nevfvudhem3eya_2_b-2000x1053.jpg","eXHWz9FSc/P5m1n8U4kDMQ==":"negan-lucille1-2000x1500.jpg","UKZks7jHyG44kjykznBtdQ==":"walking-dead-season-7-comic-con-trailer-breakdown-lucille-2000x1041.jpg","zWP/gnO9iaynKoUn+Njb2w==":"twdtv_lucille_stylized-2000x1412.jpg"}